amino/__init__.py
amino/async_client.py
amino/async_community_client.py
amino/client.py
amino/community_client.py
amino/helpers/__init__.py
amino/helpers/exceptions.py
amino/helpers/generator.py
amino/helpers/requests_builder.py
amino/objects/__init__.py
amino/objects/args.py
amino/objects/auth_data.py
amino/objects/constants.py
amino/objects/dynamic_object.py
amino/objects/media.py
amino/objects/reqObjects.py
amino/objects/argObjects/__init__.py
amino/objects/argObjects/administrators_rank.py
amino/objects/argObjects/client_types.py
amino/objects/argObjects/community_join_types.py
amino/objects/argObjects/community_modules.py
amino/objects/argObjects/embed_types.py
amino/objects/argObjects/feature_days.py
amino/objects/argObjects/gender.py
amino/objects/argObjects/leaderboard_types.py
amino/objects/argObjects/message_type.py
amino/objects/argObjects/promotion_types.py
amino/objects/argObjects/purchase_types.py
amino/objects/argObjects/qmode.py
amino/objects/argObjects/repair_method.py
amino/objects/argObjects/sorting.py
amino/objects/argObjects/sorting2.py
amino/objects/argObjects/strike_time.py
amino/objects/argObjects/upload_type.py
amino/objects/argObjects/users_types.py
amino/objects/argObjects/vc_join_permissions.py
amino/objects/ws/__init__.py
amino/objects/ws/event.py
amino/objects/ws/ws_event_types.py
amino/ws/AsyncSocket.py
amino/ws/__init__.py
amino/ws/socket.py
amino.py.api-0.4.7.dist-info/LICENSE.txt
amino.py.api-0.4.7.dist-info/METADATA
amino.py.api-0.4.7.dist-info/WHEEL
amino.py.api-0.4.7.dist-info/top_level.txt
amino.py.api-0.4.7.dist-info/RECORD
