Metadata-Version: 2.1
Name: amino.py.api
Version: 0.4.7
Summary: Library for creating amino bots and scripts.
Home-page: https://github.com/xXxCLOTIxXx/amino.py
Download-URL: https://github.com/xXxCLOTIxXx/amino.py/archive/refs/heads/main.zip
Author: Xsarz
Author-email: xsarzy@gmail.com
License: MIT
Keywords: aminoapps,aminoxz,amino,amino-bot,pymino,python-amino,amino.py,amino.api,narvii,api,python,python3,python3.x,xsarz,official,amino.py.api,amino.fix,amino.light,amino.ligt.py,AminoLightPy,medialab,aminolightpy
Classifier: Intended Audience :: Developers
Classifier: License :: OSI Approved :: MIT License
Classifier: Programming Language :: Python :: 3.9
Classifier: Programming Language :: Python :: 3.10
Classifier: Programming Language :: Python :: 3.11
Classifier: Programming Language :: Python :: 3.12
License-File: LICENSE.txt
Requires-Dist: aiohttp
Requires-Dist: json-minify
Requires-Dist: requests
Requires-Dist: ujson
Requires-Dist: websocket-client ==1.3.1
Requires-Dist: websockets
